{
    "name": "DefaultShow",
    "scenes": [
        {
            "name": "scene_0",
            "sources": [
                {
                    "name": "source_0",
                    "type": "RTMP",
                    "url": "rtmp://localhost:1936/source_a"
                }
            ]
        },
        {
            "name": "scene_1",
            "sources": [
                {
                    "name": "source_1",
                    "type": "RTMP",
                    "url": "rtmp://localhost:1936/source_a"
                }
            ]
        },
        {
            "name": "scene_2",
            "sources": [
                {
                    "name": "source_2",
                    "type": "RTMP",
                    "url": "rtmp://localhost:1936/source_a"
                }
            ]
        }
    ]
}